{
  "Posts": [
    {
      "Id": "FTomCxFk_Hc2KquLJ0pmHA",
      "AuthorId": "FNjV_ZbOYaOylLw1MLvABw",
      "CreatedOn": "2016-03-23T07:29:19Z",
      "ChannelIds": [
        "FNVt6Dkn8rHBdZFN6GDObg"
      ],
      "Title": "New Abarth spider",
      "Content": "The countdown to the New York Auto Show marches on with Fiat unwrapping the 124 Spider Elaborazione Abarth. A renamed version of the Abarth 124 Spider, it's got gunmetal accents with unique bumpers and black side skirts. Inside is leather and microfiber seats, red stitching, and custom instrument cluster. Power is from a turbo 1.4 four-cylinder with 160 hp. Brembo brakes are optional 🐜💨",
      "ShareUrl": "http://i.drive.net/p/FTomCxFk_Hc2KquLJ0pmHA",
      "Images": [
        [
          {
            "Url": "https://images.d3-x.net/RnriZz1YGCDDUQb06IOwcQYvxGE=/350x197/post/FTolzjvEQnxTSvGZfKIcEoAK0AUB.jpg",
            "W": 350,
            "H": 197
          },
          {
            "Url": "https://images.d3-x.net/fb1yPIjk1dUgtcXm1tBALnfQVxk=/700x394/post/FTolzjvEQnxTSvGZfKIcEoAK0AUB.jpg",
            "W": 700,
            "H": 394
          },
          {
            "Url": "https://images.d3-x.net/1uEbSHqgOedh_iy7ovejRq94mB0=/1280x720/post/FTolzjvEQnxTSvGZfKIcEoAK0AUB.jpg",
            "W": 1280,
            "H": 720
          }
        ]
      ],
      "Language": "en",
      "Source": "",
      "Featured": true,
      "Location": {
        "Country": "US",
        "Latitude": 37.3896045,
        "Longitude": -122.0241209,
        "Names": {
          "en": "Sunnyvale, CA"
        }
      },
      "LikeCount": 1
    },
    {
      "Id": "FToln8mU_HY2KquLJ0pmHA",
      "AuthorId": "FNjV_ZbOYaOylLw1MLvABw",
      "CreatedOn": "2016-03-23T07:21:59Z",
      "ChannelIds": [
        "FNVt_vI3QFE0TO9bcp2GCw"
      ],
      "Title": "Special 7 Series",
      "Content": "BMW Individual is making two special editions of the 7 Series based on the 750Li xDrive. The Solitaire edition, of which only six will be made, has a Metallic White finish with glass flakes embedded in the final layer of the paint, creating a deep gloss effect. The interior is fine leather and has a bar. The Master Class Edition (no pics yet) will be a one-off car. Both will have a turbo 4.4 V8 with 450 hp 😎",
      "ShareUrl": "http://i.drive.net/p/FToln8mU_HY2KquLJ0pmHA",
      "Images": [
        [
          {
            "Url": "https://images.d3-x.net/t80xH2kF51KHI2AfHAUk-JhYcOw=/350x197/post/FTolIGHk_HI2KquLJ0pmHIAK0AUB.jpg",
            "W": 350,
            "H": 197
          },
          {
            "Url": "https://images.d3-x.net/NI_-uh4HRZgmXdXE5y7dJTFeZ3E=/700x394/post/FTolIGHk_HI2KquLJ0pmHIAK0AUB.jpg",
            "W": 700,
            "H": 394
          },
          {
            "Url": "https://images.d3-x.net/xVI6znbK2TLIHP0mfFBzQmdBNj8=/1280x720/post/FTolIGHk_HI2KquLJ0pmHIAK0AUB.jpg",
            "W": 1280,
            "H": 720
          }
        ],
        [
          {
            "Url": "https://images.d3-x.net/7t1_3e4PVeVo84Ebth7UfXr6bqg=/350x197/post/FTolKpeE_HM2KquLJ0pmHIAK0AUB.jpg",
            "W": 350,
            "H": 197
          },
          {
            "Url": "https://images.d3-x.net/g981aOiK95XSPoYbF2lIwXyacvU=/700x394/post/FTolKpeE_HM2KquLJ0pmHIAK0AUB.jpg",
            "W": 700,
            "H": 394
          },
          {
            "Url": "https://images.d3-x.net/4Y-Awo5xoGE-8fDoFtdI0Z8PM2c=/1280x720/post/FTolKpeE_HM2KquLJ0pmHIAK0AUB.jpg",
            "W": 1280,
            "H": 720
          }
        ],
        [
          {
            "Url": "https://images.d3-x.net/n6eMzfyZPvsDGIi5aDj1j9jHaS4=/350x197/post/FTolPxhE_HQ2KquLJ0pmHIAK0AUB.jpg",
            "W": 350,
            "H": 197
          },
          {
            "Url": "https://images.d3-x.net/OlPvGHOjuVoqTUBSt0xQeF6ou0w=/700x394/post/FTolPxhE_HQ2KquLJ0pmHIAK0AUB.jpg",
            "W": 700,
            "H": 394
          },
          {
            "Url": "https://images.d3-x.net/Mt4-XBA9lx4lkaDSZVb8WAAcwHk=/1280x720/post/FTolPxhE_HQ2KquLJ0pmHIAK0AUB.jpg",
            "W": 1280,
            "H": 720
          }
        ],
        [
          {
            "Url": "https://images.d3-x.net/CuiyFkDf5J8G-ak1Z1lskUJRaSY=/350x197/post/FTolSygk_HU2KquLJ0pmHIAK0AUB.jpg",
            "W": 350,
            "H": 197
          },
          {
            "Url": "https://images.d3-x.net/HDeJ3q-uQgB5kNPpvKc0ia9VZzo=/700x394/post/FTolSygk_HU2KquLJ0pmHIAK0AUB.jpg",
            "W": 700,
            "H": 394
          },
          {
            "Url": "https://images.d3-x.net/XmspmJh12Y-nMhojnyyky9zMFpE=/1280x720/post/FTolSygk_HU2KquLJ0pmHIAK0AUB.jpg",
            "W": 1280,
            "H": 720
          }
        ]
      ],
      "Language": "en",
      "Source": "",
      "Featured": true,
      "Location": {
        "Country": "US",
        "Latitude": 37.3896045,
        "Longitude": -122.0241209,
        "Names": {
          "en": "Sunnyvale, CA"
        }
      },
      "LikeCount": 2
    },
    {
      "Id": "FTok3bokQntTSvGZfKIcEg",
      "AuthorId": "FNjV_ZbOYaOylLw1MLvABw",
      "CreatedOn": "2016-03-23T07:08:44Z",
      "ChannelIds": [
        "FNVt-FknQE80TO9bcp2GCw"
      ],
      "Title": "Opel GT to be made?",
      "Content": "The company unveiled the GT Concept earlier this month and the word is, they are considering putting it into production. Opel has no rear drive platform, so a production version will likely use an AWD system from the Mokka X SUV. If it gets the green light, engineers will also need a suitable transmission. The GT Concept has a three-cylinder 1.0 gas engine with 145 hp, with 0 to 62 mph in just over 8 seconds 👾",
      "ShareUrl": "http://i.drive.net/p/FTok3bokQntTSvGZfKIcEg",
      "Images": [
        [
          {
            "Url": "https://images.d3-x.net/A4FDaqWpOt1bHXJQRfMqs_38588=/350x197/post/FToktgIUQnpTSvGZfKIcEoAK0AUB.jpg",
            "W": 350,
            "H": 197
          },
          {
            "Url": "https://images.d3-x.net/mFWRm1kBrvtAR0rOb5tzUJAMHVA=/700x394/post/FToktgIUQnpTSvGZfKIcEoAK0AUB.jpg",
            "W": 700,
            "H": 394
          },
          {
            "Url": "https://images.d3-x.net/v-b-SqlDdv5S3Hpqwo3ghDeS6_Q=/1280x720/post/FToktgIUQnpTSvGZfKIcEoAK0AUB.jpg",
            "W": 1280,
            "H": 720
          }
        ]
      ],
      "Language": "en",
      "Source": "",
      "Featured": true,
      "Location": {
        "Country": "US",
        "Latitude": 37.3896045,
        "Longitude": -122.0241209,
        "Names": {
          "en": "Sunnyvale, CA"
        }
      },
      "LikeCount": 2
    },
    {
      "Id": "FTnyp95ycPC-JH7r3HJERQ",
      "AuthorId": "FM7SRrmlBA-gW5bNWjzyxg",
      "CreatedOn": "2016-03-22T16:31:15Z",
      "ChannelIds": [
        "FNVt9b5X8rPBdZFN6GDObg"
      ],
      "Title": "New BMW Flagship",
      "Content": "Nice BMW i3 promo in San Francisco 🚙⚡️",
      "ShareUrl": "http://i.drive.net/p/FTnyp95ycPC-JH7r3HJERQ",
      "Images": [
        [
          {
            "Url": "https://images.d3-x.net/Ptugpw1v6HQ4GZMxwdAmK74rUZc=/350x197/post/FTnyp7lycO--JH7r3HJERZkGvgMB.jpg",
            "W": 350,
            "H": 197
          },
          {
            "Url": "https://images.d3-x.net/f1EbyWB7NekSyRMELsiMYAeyZ_0=/700x394/post/FTnyp7lycO--JH7r3HJERZkGvgMB.jpg",
            "W": 700,
            "H": 394
          },
          {
            "Url": "https://images.d3-x.net/wxvt41eD_Ifx2S7yofX1E0cwALE=/793x446/post/FTnyp7lycO--JH7r3HJERZkGvgMB.jpg",
            "W": 793,
            "H": 446
          }
        ]
      ],
      "Language": "en",
      "Source": "",
      "Featured": true,
      "LikeCount": 1
    },
    {
      "Id": "FTnnhaDt2yqBfI99iDVnNQ",
      "AuthorId": "FPHOCZO82eGKEPZ2YQphUQ",
      "CreatedOn": "2016-03-22T13:16:40Z",
      "ChannelIds": [
        "FOZ4IwhSmzhxaG9g-XSE3w"
      ],
      "Title": "BMW M3",
      "Content": "Living in Germany and having the Nurburgring on your doorstep, you need to have a track-capable car. This owner decided to keep with the Bavarian spirit and go for a BMW. It is ready for the track with upgraded brakes, suspension, exhaust and of course: a supercharger. Running 625 hp now, it manages 0-186 mph in 27s and a top speed of 212 mph. The autobahn helps avoid speeding tickets 🏁",
      "ShareUrl": "http://i.drive.net/p/FTnnhaDt2yqBfI99iDVnNQ",
      "Images": [
        [
          {
            "Url": "https://images.d3-x.net/UdEk17UjlEF70TpgcwNdduEtsuo=/350x197/post/FTnncVHt2yaBfI99iDVnNcAHnAQB.jpg",
            "W": 350,
            "H": 197
          },
          {
            "Url": "https://images.d3-x.net/e7oOXsyvtESrG4HT8taCDkR74qU=/700x394/post/FTnncVHt2yaBfI99iDVnNcAHnAQB.jpg",
            "W": 700,
            "H": 394
          },
          {
            "Url": "https://images.d3-x.net/ExXkiikkT8XJU9N1yJcyomplL8E=/960x540/post/FTnncVHt2yaBfI99iDVnNcAHnAQB.jpg",
            "W": 960,
            "H": 540
          }
        ],
        [
          {
            "Url": "https://images.d3-x.net/5EG9P28mPxaDluwi-KwILxMrZts=/350x197/post/FTnndIHd2yeBfI99iDVnNcAHnAQB.jpg",
            "W": 350,
            "H": 197
          },
          {
            "Url": "https://images.d3-x.net/ZAsbtAq86m-SSc5cYmHGap_vP3g=/700x394/post/FTnndIHd2yeBfI99iDVnNcAHnAQB.jpg",
            "W": 700,
            "H": 394
          },
          {
            "Url": "https://images.d3-x.net/OZTkPO2nrxPNeQ0wmqclgBzLcuk=/960x540/post/FTnndIHd2yeBfI99iDVnNcAHnAQB.jpg",
            "W": 960,
            "H": 540
          }
        ],
        [
          {
            "Url": "https://images.d3-x.net/2lyOORa4I1PYU_B79txmUU2n58Y=/350x197/post/FTnneR0t2yiBfI99iDVnNcAHnAQB.jpg",
            "W": 350,
            "H": 197
          },
          {
            "Url": "https://images.d3-x.net/KrxHxmlsRW7dpMZD0UfxvN_JKxM=/700x394/post/FTnneR0t2yiBfI99iDVnNcAHnAQB.jpg",
            "W": 700,
            "H": 394
          },
          {
            "Url": "https://images.d3-x.net/oB1PJ-OcQvO2SNSbEQf_Ils-rBM=/960x540/post/FTnneR0t2yiBfI99iDVnNcAHnAQB.jpg",
            "W": 960,
            "H": 540
          }
        ],
        [
          {
            "Url": "https://images.d3-x.net/XtoKSN8cjIiU7I2w9bRAGlN1ENI=/350x197/post/FTnnfMLN2ymBfI99iDVnNcAHnAQB.jpg",
            "W": 350,
            "H": 197
          },
          {
            "Url": "https://images.d3-x.net/rbVIiDfqvBOnUh2AKTQmRirHQco=/700x394/post/FTnnfMLN2ymBfI99iDVnNcAHnAQB.jpg",
            "W": 700,
            "H": 394
          },
          {
            "Url": "https://images.d3-x.net/O9DKvb9nELLBNWMAa3tyBlx-W3M=/960x540/post/FTnnfMLN2ymBfI99iDVnNcAHnAQB.jpg",
            "W": 960,
            "H": 540
          }
        ]
      ],
      "Language": "en",
      "Source": "",
      "Featured": true,
      "Location": {
        "Country": "US",
        "Latitude": 37.3896045,
        "Longitude": -122.0241209,
        "Names": {
          "en": "Sunnyvale, CA"
        }
      },
      "LikeCount": 1
    },
    {
      "Id": "FTnnJcxgY4poD3h2NMpLVw",
      "AuthorId": "FPHOCZO82eGKEPZ2YQphUQ",
      "CreatedOn": "2016-03-22T13:10:08Z",
      "ChannelIds": [
        "FNVt9b5X8rPBdZFN6GDObg"
      ],
      "Title": "Microlino EV",
      "Content": "Micro Mobility Systems, a Swiss company, has proudly declared a retro EV version of the iconic BMW Isetta. Being classified as an L7e motorized quadricycle, the Microlino will avoid the rigorous safety and crash testing. Set to have a range of 60-75 mi, it will also achieve a top speed of 62 mph. Geneva saw 500 reservations in 13 days, with expected price of $9-13.5k. Another fashion accessory 😎",
      "ShareUrl": "http://i.drive.net/p/FTnnJcxgY4poD3h2NMpLVw",
      "Images": [],
      "Language": "en",
      "Source": "",
      "VideoUrl": "https://www.youtube.com/watch?v=8778WLCyohE&feature=youtu.be",
      "VideoHosting": "YouTube",
      "VideoId": "8778WLCyohE",
      "Featured": true,
      "Location": {
        "Country": "US",
        "Latitude": 37.3896045,
        "Longitude": -122.0241209,
        "Names": {
          "en": "Sunnyvale, CA"
        }
      },
      "LikeCount": 1
    },
    {
      "Id": "FTnmuK4QY4loD3h2NMpLVw",
      "AuthorId": "FOBhuM6mN3Qw8CgQtzKKSA",
      "CreatedOn": "2016-03-22T13:02:41Z",
      "ChannelIds": [
        "FNVuDg138rvBdZFN6GDObg"
      ],
      "Title": "New QX70 in NY show",
      "Content": "Infiniti is introducing the QX70 Limited model at the New York Auto Show this week. New for 2017 is a slightly redesigned front end with side air vents, and a stainless steel rear bumper protector. Inside it has two-tone black and white leather seats with cooling and heating options for the front passenger's. Under the hood is the standard 325 hp V6. Infiniti will start taking orders in the summer 🗓",
      "ShareUrl": "http://i.drive.net/p/FTnmuK4QY4loD3h2NMpLVw",
      "Images": [
        [
          {
            "Url": "https://images.d3-x.net/iSd3JYOuZbx9ZUqbxhweHabjC4w=/350x197/post/FTnmSf_wY4VoD3h2NMpLV4AK0AUB.jpg",
            "W": 350,
            "H": 197
          },
          {
            "Url": "https://images.d3-x.net/lSS4sod7T74csLUyvwOIpf9-nCk=/700x394/post/FTnmSf_wY4VoD3h2NMpLV4AK0AUB.jpg",
            "W": 700,
            "H": 394
          },
          {
            "Url": "https://images.d3-x.net/WWXmWE4unONcPWDV1_6GXWlfT5Y=/1280x720/post/FTnmSf_wY4VoD3h2NMpLV4AK0AUB.jpg",
            "W": 1280,
            "H": 720
          }
        ],
        [
          {
            "Url": "https://images.d3-x.net/_9eTaYvFKHbStWzwmoULyn9QXbY=/350x197/post/FTnmVHgQY4ZoD3h2NMpLV4AK0AUB.jpg",
            "W": 350,
            "H": 197
          },
          {
            "Url": "https://images.d3-x.net/YWdo0ARsnxrHVG-kxZIUWqG0Ry0=/700x394/post/FTnmVHgQY4ZoD3h2NMpLV4AK0AUB.jpg",
            "W": 700,
            "H": 394
          },
          {
            "Url": "https://images.d3-x.net/vRbXbrRYMcG2EY-BEFDgxMLVr9Y=/1280x720/post/FTnmVHgQY4ZoD3h2NMpLV4AK0AUB.jpg",
            "W": 1280,
            "H": 720
          }
        ],
        [
          {
            "Url": "https://images.d3-x.net/vSGa5F2JLDN8J2DAFbIkV5ogS9Y=/350x197/post/FTnmdMUwY4doD3h2NMpLV4AK0AUB.jpg",
            "W": 350,
            "H": 197
          },
          {
            "Url": "https://images.d3-x.net/jAmRxzfBgCRZvGoHOYrSv6FLjaI=/700x394/post/FTnmdMUwY4doD3h2NMpLV4AK0AUB.jpg",
            "W": 700,
            "H": 394
          },
          {
            "Url": "https://images.d3-x.net/lHvGGkpM-bDM1VwXrQFrXngvmng=/1280x720/post/FTnmdMUwY4doD3h2NMpLV4AK0AUB.jpg",
            "W": 1280,
            "H": 720
          }
        ],
        [
          {
            "Url": "https://images.d3-x.net/QcsdIwTOiFioDkCYJTUAawfxOXw=/350x197/post/FTnmek4gY4hoD3h2NMpLV4AK0AUB.jpg",
            "W": 350,
            "H": 197
          },
          {
            "Url": "https://images.d3-x.net/W0mvsaRTD2AOvGd-3dcoNkY1a-4=/700x394/post/FTnmek4gY4hoD3h2NMpLV4AK0AUB.jpg",
            "W": 700,
            "H": 394
          },
          {
            "Url": "https://images.d3-x.net/jw38LcAT2ujO-Z862FHnOZH0v6Y=/1280x720/post/FTnmek4gY4hoD3h2NMpLV4AK0AUB.jpg",
            "W": 1280,
            "H": 720
          }
        ]
      ],
      "Language": "en",
      "Source": "",
      "Featured": true,
      "Location": {
        "Country": "US",
        "Latitude": 37.3896045,
        "Longitude": -122.0241209,
        "Names": {
          "en": "Sunnyvale, CA"
        }
      },
      "LikeCount": 1
    },
    {
      "Id": "FTnlxql92yWBfI99iDVnNQ",
      "AuthorId": "FOBhuM6mN3Qw8CgQtzKKSA",
      "CreatedOn": "2016-03-22T12:46:10Z",
      "ChannelIds": [
        "FNVuCuZXQFU0TO9bcp2GCw"
      ],
      "Title": "Ford Shelby GT-H",
      "Content": "Would you like to rent a V8 supercar for reasonable money? This is what customers got a chance to do back in 1966 with the GT350-H. 50 years later we get the beefed-up successor in the form of the Ford Shelby GT-H, boasting more aggressive sporty looks, better exhaust, adaptive suspension, auto gearbox and loads of GT-H badging. The power rating is yet to come, but the V8 won't be timid 😉",
      "ShareUrl": "http://i.drive.net/p/FTnlxql92yWBfI99iDVnNQ",
      "Images": [
        [
          {
            "Url": "https://images.d3-x.net/9O9jsU7EQ5iEPva_dCd9vM5Slrc=/350x197/post/FTnjQsVaLtVRRW-9wV-JyIAK0AUB.jpg",
            "W": 350,
            "H": 197
          },
          {
            "Url": "https://images.d3-x.net/2fs4wJ0Yjs304FFQ25GAa0gRZx8=/700x394/post/FTnjQsVaLtVRRW-9wV-JyIAK0AUB.jpg",
            "W": 700,
            "H": 394
          },
          {
            "Url": "https://images.d3-x.net/gc2-ysaaE01xlc7pbTzioYCTWQM=/1280x720/post/FTnjQsVaLtVRRW-9wV-JyIAK0AUB.jpg",
            "W": 1280,
            "H": 720
          }
        ],
        [
          {
            "Url": "https://images.d3-x.net/lUTaFdlg1Bxa3ntKJY9IiEDF8kE=/350x197/post/FTnjScDaLtZRRW-9wV-JyIAK0AUB.jpg",
            "W": 350,
            "H": 197
          },
          {
            "Url": "https://images.d3-x.net/0JuC7l3W1uOB5HDVMvqsLQB2g7o=/700x394/post/FTnjScDaLtZRRW-9wV-JyIAK0AUB.jpg",
            "W": 700,
            "H": 394
          },
          {
            "Url": "https://images.d3-x.net/cAqFh25vhvqel6L__UouhUN__1Y=/1280x720/post/FTnjScDaLtZRRW-9wV-JyIAK0AUB.jpg",
            "W": 1280,
            "H": 720
          }
        ],
        [
          {
            "Url": "https://images.d3-x.net/IfTu-Via3h6g5hm1_LTEpxTRwes=/350x197/post/FTnjTqb6LtdRRW-9wV-JyIAK0AUB.jpg",
            "W": 350,
            "H": 197
          },
          {
            "Url": "https://images.d3-x.net/Q-ur2eJ5vFUXAVPq0k3LCXFTEdI=/700x394/post/FTnjTqb6LtdRRW-9wV-JyIAK0AUB.jpg",
            "W": 700,
            "H": 394
          },
          {
            "Url": "https://images.d3-x.net/XB3uPFq3AUzvanbm__Pnql0N21s=/1280x720/post/FTnjTqb6LtdRRW-9wV-JyIAK0AUB.jpg",
            "W": 1280,
            "H": 720
          }
        ],
        [
          {
            "Url": "https://images.d3-x.net/EZHz3Uf9rT_S_G18Q3G7v1PJo5I=/350x197/post/FTnjVYwaLthRRW-9wV-JyMAHnAQB.jpg",
            "W": 350,
            "H": 197
          },
          {
            "Url": "https://images.d3-x.net/ORTMb8mzXh7onoCz2rd-g5OorCY=/700x394/post/FTnjVYwaLthRRW-9wV-JyMAHnAQB.jpg",
            "W": 700,
            "H": 394
          },
          {
            "Url": "https://images.d3-x.net/PklCMugUrYmTFt4wOpuSt_Yu1Go=/960x540/post/FTnjVYwaLthRRW-9wV-JyMAHnAQB.jpg",
            "W": 960,
            "H": 540
          }
        ]
      ],
      "Language": "en",
      "Source": "",
      "Featured": true,
      "Location": {
        "Country": "US",
        "Latitude": 37.3896045,
        "Longitude": -122.0241209,
        "Names": {
          "en": "Sunnyvale, CA"
        }
      },
      "LikeCount": 3
    },
    {
      "Id": "FTni_xJd2ySBfI99iDVnNQ",
      "AuthorId": "FOBhuM6mN3Qw8CgQtzKKSA",
      "CreatedOn": "2016-03-22T11:57:35Z",
      "ChannelIds": [
        "FOtkyyx4Ez-siqzw4-7MgQ"
      ],
      "Title": "Quarter-mile in 8.6",
      "Content": "Heffner Performance upgraded this Huracan in the most effective way possible—turbo. Two of them, to be exact, and their effects come in the form of 1,200 hp. Add to this other setups and the car does the ¼ mile sprint in just 8.6s at 173 mph, reaching 60 in 1.9 and 100 in 3.7. Have a look at the video to see the beast in action 🚦",
      "ShareUrl": "http://i.drive.net/p/FTni_xJd2ySBfI99iDVnNQ",
      "Images": [],
      "Language": "en",
      "Source": "",
      "VideoUrl": "https://www.youtube.com/watch?v=CT1TCbjjiLM&feature=youtu.be",
      "VideoHosting": "YouTube",
      "VideoId": "CT1TCbjjiLM",
      "Featured": true,
      "Location": {
        "Country": "US",
        "Latitude": 37.3896045,
        "Longitude": -122.0241209,
        "Names": {
          "en": "Sunnyvale, CA"
        }
      },
      "LikeCount": 1
    },
    {
      "Id": "FTnib9DaLtRRRW-9wV-JyA",
      "AuthorId": "FOBhuM6mN3Qw8CgQtzKKSA",
      "CreatedOn": "2016-03-22T11:47:48Z",
      "ChannelIds": [
        "FNVt-4HXQFA0TO9bcp2GCw"
      ],
      "Title": "Malibu's fuel efficiency",
      "Content": "If we are to believe the manufacturer, the 2016 Malibu Hybrid will have a class-leading EPA fuel economy of about 47 mpg, which is notably better than the Fusion Hybrid and Camry Hybrid. The car comes with a 1.8 EcoTec and two electric motors bringing the total of 182 hp and the speeds of up to 53 mph on electric power alone and all that for about $28K ⛽️",
      "ShareUrl": "http://i.drive.net/p/FTnib9DaLtRRRW-9wV-JyA",
      "Images": [
        [
          {
            "Url": "https://images.d3-x.net/danW8t_RbGdg_l6wEYYcYikkx-A=/350x197/post/FTniR2C92yKBfI99iDVnNcAHnAQB.jpg",
            "W": 350,
            "H": 197
          },
          {
            "Url": "https://images.d3-x.net/CySpWXehfDeFSRtvP2ipzzfnEJU=/700x394/post/FTniR2C92yKBfI99iDVnNcAHnAQB.jpg",
            "W": 700,
            "H": 394
          },
          {
            "Url": "https://images.d3-x.net/S_0P3YhnvrNymrAIl7SGztqX0TE=/960x540/post/FTniR2C92yKBfI99iDVnNcAHnAQB.jpg",
            "W": 960,
            "H": 540
          }
        ],
        [
          {
            "Url": "https://images.d3-x.net/z5uIEsZr1ucvyzT6sAZO6w81NGU=/350x197/post/FTniULUt2yOBfI99iDVnNcAHnAQB.jpg",
            "W": 350,
            "H": 197
          },
          {
            "Url": "https://images.d3-x.net/5J8EdmyveF_OlI9KY4Gzay8GbtI=/700x394/post/FTniULUt2yOBfI99iDVnNcAHnAQB.jpg",
            "W": 700,
            "H": 394
          },
          {
            "Url": "https://images.d3-x.net/SorVDJEEADlle44YWc02lOo0jc0=/960x540/post/FTniULUt2yOBfI99iDVnNcAHnAQB.jpg",
            "W": 960,
            "H": 540
          }
        ]
      ],
      "Language": "en",
      "Source": "",
      "Featured": true,
      "Location": {
        "Country": "US",
        "Latitude": 37.3896045,
        "Longitude": -122.0241209,
        "Names": {
          "en": "Sunnyvale, CA"
        }
      },
      "LikeCount": 1
    },
    {
      "Id": "FTnhihwqLtNRRW-9wV-JyA",
      "AuthorId": "FPHOCZO82eGKEPZ2YQphUQ",
      "CreatedOn": "2016-03-22T11:32:07Z",
      "ChannelIds": [
        "FNVt6lEHQE00TO9bcp2GCw"
      ],
      "Title": "Teetotal Clarkson",
      "Content": "When negotiating for $15M a year deal, you need to have a sharp mind. Jeremy Clarkson decided to give up drinking for 5 months while negotiating the new show with Amazon Prime. He mentioned that the California, water and leaf drinking lawyers could call at 11PM and he wouldn't be as sharp after 3 bottles of wine. Since the deal has been penned, he continues to enjoy a beverage 🍷",
      "ShareUrl": "http://i.drive.net/p/FTnhihwqLtNRRW-9wV-JyA",
      "Images": [
        [
          {
            "Url": "https://images.d3-x.net/4aVJakQCzDweAv-7ohQcWNX21Kc=/350x197/post/FTnhbLa6LtJRRW-9wV-JyIAK0AUB.jpg",
            "W": 350,
            "H": 197
          },
          {
            "Url": "https://images.d3-x.net/pvMEXjGxn81HoaE8uPAbq4dFKU0=/700x394/post/FTnhbLa6LtJRRW-9wV-JyIAK0AUB.jpg",
            "W": 700,
            "H": 394
          },
          {
            "Url": "https://images.d3-x.net/I9m2MYDQKX2VcY2bb_urDDq-C-4=/1280x720/post/FTnhbLa6LtJRRW-9wV-JyIAK0AUB.jpg",
            "W": 1280,
            "H": 720
          }
        ]
      ],
      "Language": "en",
      "Source": "",
      "Featured": true,
      "Location": {
        "Country": "US",
        "Latitude": 37.3896045,
        "Longitude": -122.0241209,
        "Names": {
          "en": "Sunnyvale, CA"
        }
      },
      "LikeCount": 3
    },
    {
      "Id": "FTnhItx92yGBfI99iDVnNQ",
      "AuthorId": "FPHOCZO82eGKEPZ2YQphUQ",
      "CreatedOn": "2016-03-22T11:25:04Z",
      "ChannelIds": [
        "FNVuCuZXQFU0TO9bcp2GCw"
      ],
      "Title": "Gaming Lambo",
      "Content": "With such a selection of legendary super cars being revealed recently, the guys at Turn 10 Studios have a had a difficult time deciding on what to put on the cover of the next Forza game. The Lamborghini Centenario has come out on top and the computer gamers will have access to the new legend before the lucky 40 owners of the real deal. The most powerful Lamborghini ever is a fitting choice 🎮🏁",
      "ShareUrl": "http://i.drive.net/p/FTnhItx92yGBfI99iDVnNQ",
      "Images": [
        [
          {
            "Url": "https://images.d3-x.net/uXYKbEr2fiC135NCQ21F-GZ3Dbk=/350x197/post/FTnhFLTKLtFRRW-9wV-JyIAK0AUB.jpg",
            "W": 350,
            "H": 197
          },
          {
            "Url": "https://images.d3-x.net/UGGzBH4L7hMdwfR1JYBYoModku8=/700x394/post/FTnhFLTKLtFRRW-9wV-JyIAK0AUB.jpg",
            "W": 700,
            "H": 394
          },
          {
            "Url": "https://images.d3-x.net/rKpUc4q4ydGl4p4OjVn-sQkstp0=/1280x720/post/FTnhFLTKLtFRRW-9wV-JyIAK0AUB.jpg",
            "W": 1280,
            "H": 720
          }
        ]
      ],
      "Language": "en",
      "Source": "",
      "Featured": true,
      "Location": {
        "Country": "US",
        "Latitude": 37.3896045,
        "Longitude": -122.0241209,
        "Names": {
          "en": "Sunnyvale, CA"
        }
      },
      "LikeCount": 3
    },
    {
      "Id": "FTnecYjiWWVnD_B_kYheaw",
      "AuthorId": "FNfEkUUjZ6NS_bLulMhIYw",
      "CreatedOn": "2016-03-22T10:38:01Z",
      "ChannelIds": [
        "FPZjes9eoFlsJQsj_nqoYA"
      ],
      "Title": "TT creator",
      "Content": "Peter Schreyer is credited with the original Audi TT's award-winning design. He started working for another manufacturer in 2006 🏅",
      "ShareUrl": "http://i.drive.net/p/FTnecYjiWWVnD_B_kYheaw",
      "Images": [
        [
          {
            "Url": "https://images.d3-x.net/gvE7hEgP7CXUUaX5FvlGARKa2E0=/350x197/post/FTnePr0yWWRnD_B_kYhea4AK0AUB.jpg",
            "W": 350,
            "H": 197
          },
          {
            "Url": "https://images.d3-x.net/OHJmLNGoO4a41Gm4yTNrEJW0eHE=/700x394/post/FTnePr0yWWRnD_B_kYhea4AK0AUB.jpg",
            "W": 700,
            "H": 394
          },
          {
            "Url": "https://images.d3-x.net/l0-yZwOdT-Z_GmVTAjLNJ8BNtxQ=/1280x720/post/FTnePr0yWWRnD_B_kYhea4AK0AUB.jpg",
            "W": 1280,
            "H": 720
          }
        ]
      ],
      "Language": "en",
      "Source": "",
      "Featured": true,
      "Location": {
        "Country": "US",
        "Latitude": 37.3896045,
        "Longitude": -122.0241209,
        "Names": {
          "en": "Sunnyvale, CA"
        }
      },
      "Voting": {
        "Id": "FTnecb3SWWZnD_B_kYheaw",
        "Header": "Which one?",
        "Options": [
          {
            "Option": "Porsche",
            "VoteCount": 19,
            "Correct": false
          },
          {
            "Option": "Lexus",
            "VoteCount": 5,
            "Correct": false
          },
          {
            "Option": "Skoda",
            "VoteCount": 10,
            "Correct": false
          },
          {
            "Option": "Kia",
            "VoteCount": 12,
            "Correct": true
          }
        ]
      }
    },
    {
      "Id": "FTndwg6yWWNnD_B_kYheaw",
      "AuthorId": "FNjV_ZbOYaOylLw1MLvABw",
      "CreatedOn": "2016-03-22T10:26:02Z",
      "ChannelIds": [
        "FNVt6Dkn8rHBdZFN6GDObg"
      ],
      "Title": "Mini F300 by Manhart",
      "Content": "Manhart Performance unveiled the new Mini F300. It comes in British Racing Green with gold decals, 19-inch wheels and premium leather and Alcantara upholstery. It also has adjustable KW coil-over suspension. Under the hood, the turbo 2.0 has been equipped with a new intercooler, optimized ECU, and sports exhaust, which now makes 300 hp. Manhart declined to release detailed performance specs 🔧",
      "ShareUrl": "http://i.drive.net/p/FTndwg6yWWNnD_B_kYheaw",
      "Images": [
        [
          {
            "Url": "https://images.d3-x.net/g4TAa1K_E4K297YdHxgnKtDY43U=/350x197/post/FTndkUUCWV9nD_B_kYhea8AHnAQB.jpg",
            "W": 350,
            "H": 197
          },
          {
            "Url": "https://images.d3-x.net/xu_zsxOssD-_MlU4C0eVaqFQuW0=/700x394/post/FTndkUUCWV9nD_B_kYhea8AHnAQB.jpg",
            "W": 700,
            "H": 394
          },
          {
            "Url": "https://images.d3-x.net/7m4jh7UHw73CAn4r_5pFpbUoGkU=/960x540/post/FTndkUUCWV9nD_B_kYhea8AHnAQB.jpg",
            "W": 960,
            "H": 540
          }
        ],
        [
          {
            "Url": "https://images.d3-x.net/1tQKTpGdyFdJmU9zcAhmdmDAGnQ=/350x197/post/FTndmuWyWWBnD_B_kYhea8AHnAQB.jpg",
            "W": 350,
            "H": 197
          },
          {
            "Url": "https://images.d3-x.net/8ccnlbWNNCfbPf9A73CumA_WSiM=/700x394/post/FTndmuWyWWBnD_B_kYhea8AHnAQB.jpg",
            "W": 700,
            "H": 394
          },
          {
            "Url": "https://images.d3-x.net/PlR3z8WogLnurwIj8yM-H5FQLJ8=/960x540/post/FTndmuWyWWBnD_B_kYhea8AHnAQB.jpg",
            "W": 960,
            "H": 540
          }
        ],
        [
          {
            "Url": "https://images.d3-x.net/kzAlnbKZtnAqCdOVhiRSvHRe2pY=/350x197/post/FTndpIliWWFnD_B_kYhea8AHnAQB.jpg",
            "W": 350,
            "H": 197
          },
          {
            "Url": "https://images.d3-x.net/7oHlo8ZSLKPGlUbqK0KxOUFxUOw=/700x394/post/FTndpIliWWFnD_B_kYhea8AHnAQB.jpg",
            "W": 700,
            "H": 394
          },
          {
            "Url": "https://images.d3-x.net/fZwhQb16ThdmaSrMO3_A8h9VRMk=/960x540/post/FTndpIliWWFnD_B_kYhea8AHnAQB.jpg",
            "W": 960,
            "H": 540
          }
        ],
        [
          {
            "Url": "https://images.d3-x.net/yLihDjD8AcfEQ5ww2f4hyeOnAPY=/350x197/post/FTndrzqCWWJnD_B_kYhea4AK0AUB.jpg",
            "W": 350,
            "H": 197
          },
          {
            "Url": "https://images.d3-x.net/y_wJhMRIjluUFzQ0HodJ8SBxXpg=/700x394/post/FTndrzqCWWJnD_B_kYhea4AK0AUB.jpg",
            "W": 700,
            "H": 394
          },
          {
            "Url": "https://images.d3-x.net/_sJf7IU7Kf_gI2woEnh1crzg8JE=/1280x720/post/FTndrzqCWWJnD_B_kYhea4AK0AUB.jpg",
            "W": 1280,
            "H": 720
          }
        ]
      ],
      "Language": "en",
      "Source": "",
      "Featured": true,
      "Location": {
        "Country": "US",
        "Latitude": 37.3896045,
        "Longitude": -122.0241209,
        "Names": {
          "en": "Sunnyvale, CA"
        }
      },
      "LikeCount": 1
    },
    {
      "Id": "FTndYEqN2yCBfI99iDVnNQ",
      "AuthorId": "FNjV_ZbOYaOylLw1MLvABw",
      "CreatedOn": "2016-03-22T10:19:22Z",
      "ChannelIds": [
        "FNVt-FknQE80TO9bcp2GCw"
      ],
      "Title": "Bell & Ross show AeroGT",
      "Content": "French watchmaker Bell & Ross unveiled its new AeroGT concept. It's being called a modern supercar, inspired by aviation and the grand tourers of the 1950s. It's equipped with slim LED headlights, an aircraft-inspired canopy, and rearview cameras mounted on pieces meant to resemble canards. Its also got a rear vertical fin that looks like a vertical stabilizer ⌚️",
      "ShareUrl": "http://i.drive.net/p/FTndYEqN2yCBfI99iDVnNQ",
      "Images": [
        [
          {
            "Url": "https://images.d3-x.net/k179CxPVk02QnDs1mR1QmXmYaBQ=/350x197/post/FTndMjkCWV1nD_B_kYhea8AHnAQB.jpg",
            "W": 350,
            "H": 197
          },
          {
            "Url": "https://images.d3-x.net/6iiGVhcRunAjAGJQtgWR3OgeoaA=/700x394/post/FTndMjkCWV1nD_B_kYhea8AHnAQB.jpg",
            "W": 700,
            "H": 394
          },
          {
            "Url": "https://images.d3-x.net/3dNMaDYEnbbsqih07cVX6HGOPFw=/960x540/post/FTndMjkCWV1nD_B_kYhea8AHnAQB.jpg",
            "W": 960,
            "H": 540
          }
        ],
        [
          {
            "Url": "https://images.d3-x.net/mHR9_viITdfioVL2rQF6sDxDyM8=/350x197/post/FTndO5IyWV5nD_B_kYhea8AHnAQB.jpg",
            "W": 350,
            "H": 197
          },
          {
            "Url": "https://images.d3-x.net/TN_gjgvkSrjmGslXHGFVj7nFc5c=/700x394/post/FTndO5IyWV5nD_B_kYhea8AHnAQB.jpg",
            "W": 700,
            "H": 394
          },
          {
            "Url": "https://images.d3-x.net/iuuorLsormjn3jLndWEoWNiDPlw=/960x540/post/FTndO5IyWV5nD_B_kYhea8AHnAQB.jpg",
            "W": 960,
            "H": 540
          }
        ]
      ],
      "Language": "en",
      "Source": "",
      "VideoUrl": "https://www.youtube.com/watch?v=tblNNKhiqLQ&feature=youtu.be",
      "VideoHosting": "YouTube",
      "VideoId": "tblNNKhiqLQ",
      "Featured": true,
      "Location": {
        "Country": "US",
        "Latitude": 37.3896045,
        "Longitude": -122.0241209,
        "Names": {
          "en": "Sunnyvale, CA"
        }
      },
      "LikeCount": 2
    },
    {
      "Id": "FTnUdCFQWblVH1aa2IvRFw",
      "AuthorId": "FOBWsl_csrZk3x0LX2xAeQ",
      "CreatedOn": "2016-03-22T07:43:26Z",
      "ChannelIds": [
        "FNVuA2GX8rjBdZFN6GDObg",
        "FNVuEHBH8rzBdZFN6GDObg"
      ],
      "Title": "Pinzgauer 710M",
      "Content": "It is a fascinating vehicle. Designed for the Austrian Army to climb the sides of mountains, it does so pretty well. Its air cooled 2.5 L engine and low gearing will keep if off the freeway, but the incredible ground clearance, two-speed transfer case, and the ability to lock any of the three differentials separately definitely make it a mountain goat. Look for it on eBay at $11.8K BIN 🐐",
      "ShareUrl": "http://i.drive.net/p/FTnUdCFQWblVH1aa2IvRFw",
      "Images": [
        [
          {
            "Url": "https://images.d3-x.net/IwI2ILSx0IySApagkZA9El48XHM=/350x197/post/FTnUAEuAWbZVH1aa2IvRF4AK0AUB.jpg",
            "W": 350,
            "H": 197
          },
          {
            "Url": "https://images.d3-x.net/aiKpTO1tNDIcPNkbmg-nRGX7-zo=/700x394/post/FTnUAEuAWbZVH1aa2IvRF4AK0AUB.jpg",
            "W": 700,
            "H": 394
          },
          {
            "Url": "https://images.d3-x.net/HzdfIJNUP7ARlr0vHx8-EQpROzM=/1280x720/post/FTnUAEuAWbZVH1aa2IvRF4AK0AUB.jpg",
            "W": 1280,
            "H": 720
          }
        ],
        [
          {
            "Url": "https://images.d3-x.net/LLyKer6B7nv0mLgTxVipUv25PuY=/350x197/post/FTnUEFAgWbhVH1aa2IvRF4AK0AUB.jpg",
            "W": 350,
            "H": 197
          },
          {
            "Url": "https://images.d3-x.net/QRiBvZpI4uLTbJ3CfZGxUmaCaEc=/700x394/post/FTnUEFAgWbhVH1aa2IvRF4AK0AUB.jpg",
            "W": 700,
            "H": 394
          },
          {
            "Url": "https://images.d3-x.net/Y5wTguQSZ_kE-HnqCn7K7s_F31Q=/1280x720/post/FTnUEFAgWbhVH1aa2IvRF4AK0AUB.jpg",
            "W": 1280,
            "H": 720
          }
        ]
      ],
      "Language": "en",
      "Source": "",
      "Featured": true,
      "Location": {
        "Country": "US",
        "Latitude": 37.3896045,
        "Longitude": -122.0241209,
        "Names": {
          "en": "Sunnyvale, CA"
        }
      },
      "LikeCount": 1
    },
    {
      "Id": "FTnT8ABUjcaPWaH2Oef5NA",
      "AuthorId": "FOBWsl_csrZk3x0LX2xAeQ",
      "CreatedOn": "2016-03-22T07:34:25Z",
      "ChannelIds": [
        "FNVt5rPHQEw0TO9bcp2GCw"
      ],
      "Title": "100K MBs for Uber",
      "Content": "The service could be planning on making an enormous investment in its more premium UberBlack experience. The company might be planning on purchasing 100,000 Mercedes-Benz S-Class sedans. News reports state that Uber has placed a long-term order with Daimler to the tune of \"at least 100,000\" S-Class sedans. At $100K each that makes it potentially a $10 billion deal 💰",
      "ShareUrl": "http://i.drive.net/p/FTnT8ABUjcaPWaH2Oef5NA",
      "Images": [
        [
          {
            "Url": "https://images.d3-x.net/yA9POVWrz1ASsvMJ7L6F8QDlBTo=/350x197/post/FTnTz9_UjcWPWaH2Oef5NIAK0AUB.jpg",
            "W": 350,
            "H": 197
          },
          {
            "Url": "https://images.d3-x.net/EKaHzeNgOsDfcD70vwyjdOTdKAE=/700x394/post/FTnTz9_UjcWPWaH2Oef5NIAK0AUB.jpg",
            "W": 700,
            "H": 394
          },
          {
            "Url": "https://images.d3-x.net/YwwvlrqO_STGcZccPeSF6Zf8ASI=/1280x720/post/FTnTz9_UjcWPWaH2Oef5NIAK0AUB.jpg",
            "W": 1280,
            "H": 720
          }
        ]
      ],
      "Language": "en",
      "Source": "",
      "Featured": true,
      "Location": {
        "Country": "US",
        "Latitude": 37.3896045,
        "Longitude": -122.0241209,
        "Names": {
          "en": "Sunnyvale, CA"
        }
      },
      "LikeCount": 1
    },
    {
      "Id": "FTmxfsE6WAAUnVOQ7Z2kUw",
      "AuthorId": "FOBhuM6mN3Qw8CgQtzKKSA",
      "CreatedOn": "2016-03-21T21:32:29Z",
      "ChannelIds": [
        "FNVuDg138rvBdZFN6GDObg",
        "FOIFE4_nEofCtdpCSNcRQg"
      ],
      "Title": "GLC 63 to come?",
      "Content": "The car in the photos looks like a Mercedes-AMG GLC 43 with a bit more of a bumper, but it’s pushed by a V8 that should propel the 63 version of the crossover. The power ratings of the engine should be the same as those in the C63 and C63 S, which are at 469 hp and 510 hp respectively. If you like it, you'll be glad to know that it’ll be presented by the end of the year 🎄",
      "ShareUrl": "http://i.drive.net/p/FTmxfsE6WAAUnVOQ7Z2kUw",
      "Images": [
        [
          {
            "Url": "https://images.d3-x.net/4fYFL0sQOX48_1Zz-d2F0EZtIak=/350x197/post/FTmxWi8aV_4UnVOQ7Z2kU4AK0AUB.jpg",
            "W": 350,
            "H": 197
          },
          {
            "Url": "https://images.d3-x.net/qF_eRWnrlBgHPLEyzq_TpYyzPVo=/700x394/post/FTmxWi8aV_4UnVOQ7Z2kU4AK0AUB.jpg",
            "W": 700,
            "H": 394
          },
          {
            "Url": "https://images.d3-x.net/QuQCpxutyVCTs_aHBTRkydWLcHQ=/1280x720/post/FTmxWi8aV_4UnVOQ7Z2kU4AK0AUB.jpg",
            "W": 1280,
            "H": 720
          }
        ],
        [
          {
            "Url": "https://images.d3-x.net/67vU5J5ZO1-lTa2zHt2GEH6Oztw=/350x197/post/FTmxbQf6V_8UnVOQ7Z2kU4AK0AUB.jpg",
            "W": 350,
            "H": 197
          },
          {
            "Url": "https://images.d3-x.net/dWrhdFOW8XFg5POoEW4CgrONylA=/700x394/post/FTmxbQf6V_8UnVOQ7Z2kU4AK0AUB.jpg",
            "W": 700,
            "H": 394
          },
          {
            "Url": "https://images.d3-x.net/XrWPPZYYw0JhgxR-ac-1hzFomNc=/1280x720/post/FTmxbQf6V_8UnVOQ7Z2kU4AK0AUB.jpg",
            "W": 1280,
            "H": 720
          }
        ]
      ],
      "Language": "en",
      "Source": "",
      "Featured": true,
      "Location": {
        "Country": "US",
        "Latitude": 37.3896045,
        "Longitude": -122.0241209,
        "Names": {
          "en": "Sunnyvale, CA"
        }
      },
      "LikeCount": 1
    },
    {
      "Id": "FTmw-7NqV_0UnVOQ7Z2kUw",
      "AuthorId": "FOBWsl_csrZk3x0LX2xAeQ",
      "CreatedOn": "2016-03-21T21:23:32Z",
      "ChannelIds": [
        "FNVuDyinQFc0TO9bcp2GCw"
      ],
      "Title": "GM's 10 speed auto",
      "Content": "While Mercedes is happy with 9, GM is taking it to 10—10 speeds that is. GM’s newest automatic will be debut in the ‘17 Camaro ZL1 and will then find its way into 7 of GM’s other vehicles, likely the Escalade, Suburban/Tahoe and versions of the Silverado and Sierra pickups. The box was developed with Ford, who will debut it in the Raptor ⚙",
      "ShareUrl": "http://i.drive.net/p/FTmw-7NqV_0UnVOQ7Z2kUw",
      "Images": [
        [
          {
            "Url": "https://images.d3-x.net/3AZ25RFqvAhhHWm_DcJimsbv61g=/350x197/post/FTmw7TCrVUrm6hLgclat0cAHnAQB.jpg",
            "W": 350,
            "H": 197
          },
          {
            "Url": "https://images.d3-x.net/tb7vZvae6u57Le9lBNdxaAMw6Xw=/700x394/post/FTmw7TCrVUrm6hLgclat0cAHnAQB.jpg",
            "W": 700,
            "H": 394
          },
          {
            "Url": "https://images.d3-x.net/D2tmZPJGVGLYzWXwORXo64wSWek=/960x540/post/FTmw7TCrVUrm6hLgclat0cAHnAQB.jpg",
            "W": 960,
            "H": 540
          }
        ]
      ],
      "Language": "en",
      "Source": "",
      "Featured": true,
      "Location": {
        "Country": "US",
        "Latitude": 37.3896045,
        "Longitude": -122.0241209,
        "Names": {
          "en": "Sunnyvale, CA"
        }
      },
      "LikeCount": 1
    },
    {
      "Id": "FTmwY_5bVUnm6hLgclat0Q",
      "AuthorId": "FPHOCZO82eGKEPZ2YQphUQ",
      "CreatedOn": "2016-03-21T21:13:11Z",
      "ChannelIds": [
        "FOZ4IwhSmzhxaG9g-XSE3w"
      ],
      "Title": "Porsche Speedster replica",
      "Content": "Modifying a classic Porsche is for the rich and famous. When you have the itch, here is an awesome solution—the '57 Speedster replica. This one has been built above and beyond the normal tacky replica. 153 hp from a very clean 1.9 VW. Better attention to detail than the real deal 👌",
      "ShareUrl": "http://i.drive.net/p/FTmwY_5bVUnm6hLgclat0Q",
      "Images": [
        [
          {
            "Url": "https://images.d3-x.net/OnvkOZ5lR4zeNDdYZEB1YS9sZ7Y=/350x197/post/FTmwEND7VUXm6hLgclat0cAHnAQB.jpg",
            "W": 350,
            "H": 197
          },
          {
            "Url": "https://images.d3-x.net/9LTTc-s0gkHp_EPYL4A2zfNeX5A=/700x394/post/FTmwEND7VUXm6hLgclat0cAHnAQB.jpg",
            "W": 700,
            "H": 394
          },
          {
            "Url": "https://images.d3-x.net/v05g-_q79873_y6j4EicvZ0wcfU=/960x540/post/FTmwEND7VUXm6hLgclat0cAHnAQB.jpg",
            "W": 960,
            "H": 540
          }
        ],
        [
          {
            "Url": "https://images.d3-x.net/vfYm03SQgVeUfiMPaMOKF8dtfTI=/350x197/post/FTmwHV5bVUbm6hLgclat0cAHnAQB.jpg",
            "W": 350,
            "H": 197
          },
          {
            "Url": "https://images.d3-x.net/Qaq17uPPEHgUdE8NDJY_3_1HHwU=/700x394/post/FTmwHV5bVUbm6hLgclat0cAHnAQB.jpg",
            "W": 700,
            "H": 394
          },
          {
            "Url": "https://images.d3-x.net/dkgQjd4bEpOgYvV6wK1-DhntJ7Q=/960x540/post/FTmwHV5bVUbm6hLgclat0cAHnAQB.jpg",
            "W": 960,
            "H": 540
          }
        ],
        [
          {
            "Url": "https://images.d3-x.net/5J3Mn7BubPRv3rw9uG0r-tm37PY=/350x197/post/FTmwLc_bVUfm6hLgclat0YAK0AUB.jpg",
            "W": 350,
            "H": 197
          },
          {
            "Url": "https://images.d3-x.net/GKsA64Vmm8J7n04vepfrq2m4YMI=/700x394/post/FTmwLc_bVUfm6hLgclat0YAK0AUB.jpg",
            "W": 700,
            "H": 394
          },
          {
            "Url": "https://images.d3-x.net/l6oAfPKewARzBu7dYIERRQ-hYuI=/1280x720/post/FTmwLc_bVUfm6hLgclat0YAK0AUB.jpg",
            "W": 1280,
            "H": 720
          }
        ],
        [
          {
            "Url": "https://images.d3-x.net/53Mt4Y5diQAA6sHxcqMFloA8lZ8=/350x197/post/FTmwNIULVUjm6hLgclat0YAK0AUB.jpg",
            "W": 350,
            "H": 197
          },
          {
            "Url": "https://images.d3-x.net/w_noq-_s6OhqNEzdh0jvVn84pfY=/700x394/post/FTmwNIULVUjm6hLgclat0YAK0AUB.jpg",
            "W": 700,
            "H": 394
          },
          {
            "Url": "https://images.d3-x.net/vxxRgr2cwTaBiiNZ-za8UD29Pcg=/1280x720/post/FTmwNIULVUjm6hLgclat0YAK0AUB.jpg",
            "W": 1280,
            "H": 720
          }
        ]
      ],
      "Language": "en",
      "Source": "",
      "Featured": true,
      "Location": {
        "Country": "US",
        "Latitude": 37.3896045,
        "Longitude": -122.0241209,
        "Names": {
          "en": "Sunnyvale, CA"
        }
      },
      "LikeCount": 2
    },
    {
      "Id": "FTmvz-EbVUTm6hLgclat0Q",
      "AuthorId": "FOBWsl_csrZk3x0LX2xAeQ",
      "CreatedOn": "2016-03-21T21:03:04Z",
      "ChannelIds": [
        "FOIFE4_nEofCtdpCSNcRQg"
      ],
      "Title": "New Panamera seen",
      "Content": "The 2016 Porsche Panamera appeared at the Nurburgring pretty much in its final form. While external dimensions remain the same, engineers have moved weight forward to improve handling and integrated more high-strength steel to save 220 lbs. Don't look for any news on the engine front but it’s fairly certain a Shooting Brake version will appear shortly after the sedan makes its debut 📷",
      "ShareUrl": "http://i.drive.net/p/FTmvz-EbVUTm6hLgclat0Q",
      "Images": [
        [
          {
            "Url": "https://images.d3-x.net/kup7s5wetE3yNtmz_AARcRXnb70=/350x197/post/FTmvoCkLVULm6hLgclat0YAK0AUB.jpg",
            "W": 350,
            "H": 197
          },
          {
            "Url": "https://images.d3-x.net/-91GONrje8GgOk_9q3R68x5ix8E=/700x394/post/FTmvoCkLVULm6hLgclat0YAK0AUB.jpg",
            "W": 700,
            "H": 394
          },
          {
            "Url": "https://images.d3-x.net/8N9yNRMlVGCdJGP0I37SjPrEXNQ=/1280x720/post/FTmvoCkLVULm6hLgclat0YAK0AUB.jpg",
            "W": 1280,
            "H": 720
          }
        ],
        [
          {
            "Url": "https://images.d3-x.net/UrK6IfCsE9eFjzVVF6vwDHm9FSo=/350x197/post/FTmvuIx7VUPm6hLgclat0YAK0AUB.jpg",
            "W": 350,
            "H": 197
          },
          {
            "Url": "https://images.d3-x.net/XfQkWOESD4VdaeIpEq7x-rQ2ghI=/700x394/post/FTmvuIx7VUPm6hLgclat0YAK0AUB.jpg",
            "W": 700,
            "H": 394
          },
          {
            "Url": "https://images.d3-x.net/9dV7NsM9dwYpMiesZVaQ8cNrbyo=/1280x720/post/FTmvuIx7VUPm6hLgclat0YAK0AUB.jpg",
            "W": 1280,
            "H": 720
          }
        ]
      ],
      "Language": "en",
      "Source": "",
      "Featured": true,
      "Location": {
        "Country": "US",
        "Latitude": 37.3896045,
        "Longitude": -122.0241209,
        "Names": {
          "en": "Sunnyvale, CA"
        }
      },
      "LikeCount": 1
    },
    {
      "Id": "FTmjzWNTBINIBifZNm0c2g",
      "AuthorId": "FPHOCZO82eGKEPZ2YQphUQ",
      "CreatedOn": "2016-03-21T17:33:11Z",
      "ChannelIds": [
        "FNVuA2GX8rjBdZFN6GDObg"
      ],
      "Title": "Ford T tours the world",
      "Content": "Extreme dedication. A couple has almost completed a round the world trip in a 1915 Model T. In 2012 they managed 14K mi from Netherlands to Cape Town. A year later USA and Canada were covered in 17K mi and following that 16K mi in South America. Unfortunately an accident with a truck in Belgium stopped the trip in 2014. They are vowing to restore and complete the mission in 2017. Keep trucking 👍",
      "ShareUrl": "http://i.drive.net/p/FTmjzWNTBINIBifZNm0c2g",
      "Images": [],
      "Language": "en",
      "Source": "",
      "VideoUrl": "https://www.youtube.com/watch?v=hhwVjJvEjAs&feature=youtu.be",
      "VideoHosting": "YouTube",
      "VideoId": "hhwVjJvEjAs",
      "Featured": true,
      "Location": {
        "Country": "US",
        "Latitude": 37.3896045,
        "Longitude": -122.0241209,
        "Names": {
          "en": "Sunnyvale, CA"
        }
      },
      "LikeCount": 1
    },
    {
      "Id": "FTmjc3i0Z4um2RdKvTV1dA",
      "AuthorId": "FOBhuM6mN3Qw8CgQtzKKSA",
      "CreatedOn": "2016-03-21T17:27:03Z",
      "ChannelIds": [
        "FNVt5rPHQEw0TO9bcp2GCw",
        "FNVuCuZXQFU0TO9bcp2GCw"
      ],
      "Title": "NSX record",
      "Content": "The Viper has been the most expensive car built in the US, but the 2017 NSX should start at $156,000 and go all the way up to $205,700. And it’ll stay at the top for a while, since the only American car that should cost about twice as much, the Ford GT, will actually be made in Canada. Moreover, a future convertible NSX, or even the Type R one should increase the margin 💰",
      "ShareUrl": "http://i.drive.net/p/FTmjc3i0Z4um2RdKvTV1dA",
      "Images": [
        [
          {
            "Url": "https://images.d3-x.net/jF3jJXqwn4Vtr1PNcQP_xIRen5Q=/350x197/post/FTmjWe30Z4qm2RdKvTV1dIAK0AUB.jpg",
            "W": 350,
            "H": 197
          },
          {
            "Url": "https://images.d3-x.net/Y3uUbla8wV48bfXPH2kxd2vy2mE=/700x394/post/FTmjWe30Z4qm2RdKvTV1dIAK0AUB.jpg",
            "W": 700,
            "H": 394
          },
          {
            "Url": "https://images.d3-x.net/hrc2O7-g_SfMn7J97CpDxcoDEUU=/1280x720/post/FTmjWe30Z4qm2RdKvTV1dIAK0AUB.jpg",
            "W": 1280,
            "H": 720
          }
        ]
      ],
      "Language": "en",
      "Source": "",
      "Featured": true,
      "Location": {
        "Country": "US",
        "Latitude": 37.3896045,
        "Longitude": -122.0241209,
        "Names": {
          "en": "Sunnyvale, CA"
        }
      },
      "LikeCount": 2
    },
    {
      "Id": "FTme9AnU00AHBgWqK7mpNA",
      "AuthorId": "FM7SRrmlBA-gW5bNWjzyxg",
      "CreatedOn": "2016-03-21T16:08:27Z",
      "ChannelIds": [
        "FNVuCH5XQFQ0TO9bcp2GCw"
      ],
      "Title": "One more autonomous car",
      "Content": "Did you know that Swedish company Ericsson is working on self-driving technology? This Ford Escape with LIDAR on the roof was spotted in Mountain View, CA 🚙🇸🇪",
      "ShareUrl": "http://i.drive.net/p/FTme9AnU00AHBgWqK7mpNA",
      "Images": [
        [
          {
            "Url": "https://images.d3-x.net/YhAQRzHSW2aF_jvJ4noDl4rN1wI=/350x197/post/FTme899k0z8HBgWqK7mpNIQH-gMB.jpg",
            "W": 350,
            "H": 197
          },
          {
            "Url": "https://images.d3-x.net/Hfzsf3-6kU-8Oq2CGvPKYY8B3as=/700x394/post/FTme899k0z8HBgWqK7mpNIQH-gMB.jpg",
            "W": 700,
            "H": 394
          },
          {
            "Url": "https://images.d3-x.net/a2UVUvdB-38G4VGS4N2jrse6Xps=/900x506/post/FTme899k0z8HBgWqK7mpNIQH-gMB.jpg",
            "W": 900,
            "H": 506
          }
        ]
      ],
      "Language": "en",
      "Source": "",
      "Featured": true,
      "LikeCount": 2
    },
    {
      "Id": "FTmba3ZMhCwnT1yfcIMzUA",
      "AuthorId": "FPHOCZO82eGKEPZ2YQphUQ",
      "CreatedOn": "2016-03-21T15:06:41Z",
      "ChannelIds": [
        "FOtkyyx4Ez-siqzw4-7MgQ"
      ],
      "Title": "Alonso сrash",
      "Content": "Cats have 9 lives and Alonso also seems to be part feline. Following his monstrous crash at the Australian GP, this weekend, he has managed to walk away virtually unscathed. Admitting that he'll most likely be needing some ice packs, the terrifying roll was caused when he hit the rear of Esteban Gutierrez's Haas while battling for 19th position. His '03 Brazil crash has now been trumped 🏎",
      "ShareUrl": "http://i.drive.net/p/FTmba3ZMhCwnT1yfcIMzUA",
      "Images": [],
      "Language": "en",
      "Source": "",
      "VideoUrl": "http://www.youtube.com/watch?v=as_rZPJS8KM",
      "VideoHosting": "YouTube",
      "VideoId": "as_rZPJS8KM",
      "Featured": true,
      "Location": {
        "Country": "US",
        "Latitude": 37.3896045,
        "Longitude": -122.0241209,
        "Names": {
          "en": "Sunnyvale, CA"
        }
      },
      "LikeCount": 2
    },
    {
      "Id": "FTmasxLY0KkQ1NoUgaxf4g",
      "AuthorId": "FPHOCZO82eGKEPZ2YQphUQ",
      "CreatedOn": "2016-03-21T14:54:06Z",
      "ChannelIds": [
        "FNVt_vI3QFE0TO9bcp2GCw",
        "FNVuDMJXQFY0TO9bcp2GCw"
      ],
      "Title": "Continental GT Black Speed",
      "Content": "Introducing a new limited-run of 10 from Mulliner. Bentley brought the \"Black Speed\" to reveal at the Australian GP. Despite the images, the latest Continental GT special is a RHD only offering and has been billed as the \"most aggressive car\" they've made. Prices start at $400K and the fully loaded monster comes at $455K. Keep Alonso out of this one ✋",
      "ShareUrl": "http://i.drive.net/p/FTmasxLY0KkQ1NoUgaxf4g",
      "Images": [
        [
          {
            "Url": "https://images.d3-x.net/hT-X6LT3GSgtLyjcPa3jJ0q29Mg=/350x197/post/FTmacAtY0KUQ1NoUgaxf4sAHnAQB.jpg",
            "W": 350,
            "H": 197
          },
          {
            "Url": "https://images.d3-x.net/UC4mg1kdEWuRDxT5Kg19vMC4vTU=/700x394/post/FTmacAtY0KUQ1NoUgaxf4sAHnAQB.jpg",
            "W": 700,
            "H": 394
          },
          {
            "Url": "https://images.d3-x.net/wQzW-Ahch-NY1lQsfXEDaDHRGRY=/960x540/post/FTmacAtY0KUQ1NoUgaxf4sAHnAQB.jpg",
            "W": 960,
            "H": 540
          }
        ],
        [
          {
            "Url": "https://images.d3-x.net/ead9EeFoK5-e41lyyEK5HUNhd14=/350x197/post/FTmadcD40KYQ1NoUgaxf4sAHnAQB.jpg",
            "W": 350,
            "H": 197
          },
          {
            "Url": "https://images.d3-x.net/RIyPytFNE6IcZKnMnF-ZBqQUHpA=/700x394/post/FTmadcD40KYQ1NoUgaxf4sAHnAQB.jpg",
            "W": 700,
            "H": 394
          },
          {
            "Url": "https://images.d3-x.net/NTfO6E6WiFJ5JAqJUrxpo3X2NT4=/960x540/post/FTmadcD40KYQ1NoUgaxf4sAHnAQB.jpg",
            "W": 960,
            "H": 540
          }
        ],
        [
          {
            "Url": "https://images.d3-x.net/7Ea23Wl6ZpWCgZfPHDRvgNo1Ohg=/350x197/post/FTmafScY0KcQ1NoUgaxf4oAK0AUB.jpg",
            "W": 350,
            "H": 197
          },
          {
            "Url": "https://images.d3-x.net/ws7I-5H0LPep-oTN5CcRXX1j7wI=/700x394/post/FTmafScY0KcQ1NoUgaxf4oAK0AUB.jpg",
            "W": 700,
            "H": 394
          },
          {
            "Url": "https://images.d3-x.net/SRZ0og2N6aPnSLjaQ2dicg7ZZGg=/1280x720/post/FTmafScY0KcQ1NoUgaxf4oAK0AUB.jpg",
            "W": 1280,
            "H": 720
          }
        ],
        [
          {
            "Url": "https://images.d3-x.net/kEQatHux5_FREuhmFTC276HIN54=/350x197/post/FTma5bmMhCsnT1yfcIMzUIAK0AUB.jpg",
            "W": 350,
            "H": 197
          },
          {
            "Url": "https://images.d3-x.net/TqlPHuKg_qmfkmvGhrF0HQzbJhQ=/700x394/post/FTma5bmMhCsnT1yfcIMzUIAK0AUB.jpg",
            "W": 700,
            "H": 394
          },
          {
            "Url": "https://images.d3-x.net/IrSGqMmuYocRqaJLE6_jQeDiJtA=/1280x720/post/FTma5bmMhCsnT1yfcIMzUIAK0AUB.jpg",
            "W": 1280,
            "H": 720
          }
        ]
      ],
      "Language": "en",
      "Source": "",
      "Featured": true,
      "Location": {
        "Country": "US",
        "Latitude": 37.3896045,
        "Longitude": -122.0241209,
        "Names": {
          "en": "Sunnyvale, CA"
        }
      },
      "LikeCount": 3
    },
    {
      "Id": "FTmaSzGMhCknT1yfcIMzUA",
      "AuthorId": "FNfEkUUjZ6NS_bLulMhIYw",
      "CreatedOn": "2016-03-21T14:47:01Z",
      "ChannelIds": [
        "FPZjes9eoFlsJQsj_nqoYA"
      ],
      "Title": "Mercedes 500K",
      "Content": "The 500K is one of the most highly-prized Mercedes-Benzes of all 🏆",
      "ShareUrl": "http://i.drive.net/p/FTmaSzGMhCknT1yfcIMzUA",
      "Images": [
        [
          {
            "Url": "https://images.d3-x.net/165DUgQ1Keye5XqHhobnpIknVEo=/350x197/post/FTmaGGJMhCgnT1yfcIMzUMAHnAQB.jpg",
            "W": 350,
            "H": 197
          },
          {
            "Url": "https://images.d3-x.net/E5V43Wf38VApQGGraLdjpJEhjv8=/700x394/post/FTmaGGJMhCgnT1yfcIMzUMAHnAQB.jpg",
            "W": 700,
            "H": 394
          },
          {
            "Url": "https://images.d3-x.net/UI_fBnCtzXI3d0f8dhv51Od4v8s=/960x540/post/FTmaGGJMhCgnT1yfcIMzUMAHnAQB.jpg",
            "W": 960,
            "H": 540
          }
        ]
      ],
      "Language": "en",
      "Source": "",
      "Featured": true,
      "Location": {
        "Country": "US",
        "Latitude": 37.3896045,
        "Longitude": -122.0241209,
        "Names": {
          "en": "Sunnyvale, CA"
        }
      },
      "LikeCount": 3,
      "Voting": {
        "Id": "FTmaS5TI0KQQ1NoUgaxf4g",
        "Header": "Which features could it boast?",
        "Options": [
          {
            "Option": "Supercharger",
            "VoteCount": 14,
            "Correct": true
          },
          {
            "Option": "Disc brakes",
            "VoteCount": 18,
            "Correct": false
          },
          {
            "Option": "Fuel injection",
            "VoteCount": 19,
            "Correct": false
          }
        ]
      }
    },
    {
      "Id": "FTmXfEfo0KMQ1NoUgaxf4g",
      "AuthorId": "FOBhuM6mN3Qw8CgQtzKKSA",
      "CreatedOn": "2016-03-21T13:57:56Z",
      "ChannelIds": [
        "FNVt6Dkn8rHBdZFN6GDObg"
      ],
      "Title": "220i by mcchip-dkr",
      "Content": "German tuner has a solution for the 220i driver that wants more. The 2.0 turbo has potential but the standard 184 hp needs more. Stage one offers 255 hp for a reasonable $1250 and stage 2 brings 320 hp for a more substantial $7.2K, that includes a larger turbo. Their demo car rides on coilovers, 19\" split rims and a branded wrap. Easier to buy a 235i? 🤔",
      "ShareUrl": "http://i.drive.net/p/FTmXfEfo0KMQ1NoUgaxf4g",
      "Images": [
        [
          {
            "Url": "https://images.d3-x.net/_bnCiFxpjQYIT6lbxI-VUrgSwIE=/350x197/post/FTmXLXyY0J0Q1NoUgaxf4oAK0AUB.jpg",
            "W": 350,
            "H": 197
          },
          {
            "Url": "https://images.d3-x.net/jAqGTKlGNeLbUnRbCiwCdwQX8ys=/700x394/post/FTmXLXyY0J0Q1NoUgaxf4oAK0AUB.jpg",
            "W": 700,
            "H": 394
          },
          {
            "Url": "https://images.d3-x.net/VQBGscLoS4wF_FcxQbUxbG-k0Pc=/1280x720/post/FTmXLXyY0J0Q1NoUgaxf4oAK0AUB.jpg",
            "W": 1280,
            "H": 720
          }
        ],
        [
          {
            "Url": "https://images.d3-x.net/kezU9TiQDWakQsHl2T6Vy9FTnWc=/350x197/post/FTmXNRSI0J4Q1NoUgaxf4oAK0AUB.jpg",
            "W": 350,
            "H": 197
          },
          {
            "Url": "https://images.d3-x.net/SoNYrpidnm6x8UEwCtOwLBrpcp4=/700x394/post/FTmXNRSI0J4Q1NoUgaxf4oAK0AUB.jpg",
            "W": 700,
            "H": 394
          },
          {
            "Url": "https://images.d3-x.net/c1OIR5vDBkHSxFcOayEh_qsgP50=/1280x720/post/FTmXNRSI0J4Q1NoUgaxf4oAK0AUB.jpg",
            "W": 1280,
            "H": 720
          }
        ],
        [
          {
            "Url": "https://images.d3-x.net/-G4R9s7SgxVHD6fc0dcc6NxlSRI=/350x197/post/FTmXRAV40KEQ1NoUgaxf4oAK0AUB.jpg",
            "W": 350,
            "H": 197
          },
          {
            "Url": "https://images.d3-x.net/L-Syl3RQ9QYsJkxTLMo5rKCVwh8=/700x394/post/FTmXRAV40KEQ1NoUgaxf4oAK0AUB.jpg",
            "W": 700,
            "H": 394
          },
          {
            "Url": "https://images.d3-x.net/NkGGZi80pITI-hdlZRaJFfBdh7s=/1280x720/post/FTmXRAV40KEQ1NoUgaxf4oAK0AUB.jpg",
            "W": 1280,
            "H": 720
          }
        ],
        [
          {
            "Url": "https://images.d3-x.net/ycihRldLAj_IZjnjcxd0qRzY-RI=/350x197/post/FTmXTICY0KIQ1NoUgaxf4oAK0AUB.jpg",
            "W": 350,
            "H": 197
          },
          {
            "Url": "https://images.d3-x.net/Ufia9-LkUof1mmiGqpzHa1qFwjE=/700x394/post/FTmXTICY0KIQ1NoUgaxf4oAK0AUB.jpg",
            "W": 700,
            "H": 394
          },
          {
            "Url": "https://images.d3-x.net/jtMUHKCNPuqj5hsbT4CnJvDuJ_k=/1280x720/post/FTmXTICY0KIQ1NoUgaxf4oAK0AUB.jpg",
            "W": 1280,
            "H": 720
          }
        ]
      ],
      "Language": "en",
      "Source": "",
      "Featured": true,
      "Location": {
        "Country": "US",
        "Latitude": 37.3896045,
        "Longitude": -122.0241209,
        "Names": {
          "en": "Sunnyvale, CA"
        }
      },
      "LikeCount": 1
    },
    {
      "Id": "FTmXDOkI0JwQ1NoUgaxf4g",
      "AuthorId": "FOBhuM6mN3Qw8CgQtzKKSA",
      "CreatedOn": "2016-03-21T13:50:20Z",
      "ChannelIds": [
        "FNVt5Ptn8rDBdZFN6GDObg"
      ],
      "Title": "Ford GT documentary",
      "Content": "The documentary will come in several chapters and the first one has been released. It’s called “The Decision” and it portrays the rivalry that sparked the Ford GT. After Henry Ford was unable to purchase Ferrari, his anger towards Enzo Ferrari inspired years of development that would result in 1-2-3 1966 victory at Le Mans for the GT. See it below and stay tuned for the rest 🎞",
      "ShareUrl": "http://i.drive.net/p/FTmXDOkI0JwQ1NoUgaxf4g",
      "Images": [],
      "Language": "en",
      "Source": "",
      "VideoUrl": "https://www.youtube.com/watch?v=qd-HyazYbCU&feature=youtu.be",
      "VideoHosting": "YouTube",
      "VideoId": "qd-HyazYbCU",
      "Featured": true,
      "Location": {
        "Country": "US",
        "Latitude": 37.3896045,
        "Longitude": -122.0241209,
        "Names": {
          "en": "Sunnyvale, CA"
        }
      },
      "LikeCount": 3
    },
    {
      "Id": "FTmWr1Jkc-n5z2EMl3_BsQ",
      "AuthorId": "FOBhuM6mN3Qw8CgQtzKKSA",
      "CreatedOn": "2016-03-21T13:43:56Z",
      "ChannelIds": [
        "FNVt9b5X8rPBdZFN6GDObg",
        "FNVuDyinQFc0TO9bcp2GCw"
      ],
      "Title": "EV powered by road",
      "Content": "Scientists at Japanese Toyohashi University have been working on ways to make batteries less important in EVs by enabling steel wires from the tires draw energy from steel paths in the road. Although this does work, there are loads of problems, including the amount of energy gained and huge infrastructure development. However, if this proves worthy, it could be a revolution 🚗⚡️",
      "ShareUrl": "http://i.drive.net/p/FTmWr1Jkc-n5z2EMl3_BsQ",
      "Images": [
        [
          {
            "Url": "https://images.d3-x.net/5_QIR96cknWZlEgDxed_A9Dobr4=/350x197/post/FTmWhmUkc-j5z2EMl3_BscAHnAQB.jpg",
            "W": 350,
            "H": 197
          },
          {
            "Url": "https://images.d3-x.net/AFYM66ApZoh0aw0CXBfQH-uCh4U=/700x394/post/FTmWhmUkc-j5z2EMl3_BscAHnAQB.jpg",
            "W": 700,
            "H": 394
          },
          {
            "Url": "https://images.d3-x.net/DHlF06pauAfMu5KWEQf5o_F3yuY=/960x540/post/FTmWhmUkc-j5z2EMl3_BscAHnAQB.jpg",
            "W": 960,
            "H": 540
          }
        ]
      ],
      "Language": "en",
      "Source": "",
      "Featured": true,
      "Location": {
        "Country": "US",
        "Latitude": 37.3896045,
        "Longitude": -122.0241209,
        "Names": {
          "en": "Sunnyvale, CA"
        }
      },
      "LikeCount": 2
    },
    {
      "Id": "FTjiRNCWtUW1NIV32h3e0A",
      "AuthorId": "FM7SRrmlBA-gW5bNWjzyxg",
      "CreatedOn": "2016-03-19T09:10:57Z",
      "ChannelIds": [
        "FNVt9b5X8rPBdZFN6GDObg"
      ],
      "Title": "Electric Orange",
      "Content": "Cool looking Tesla Roadster spotted in Los Altos, CA 🍊",
      "ShareUrl": "http://i.drive.net/p/FTjiRNCWtUW1NIV32h3e0A",
      "Images": [
        [
          {
            "Url": "https://images.d3-x.net/ieXuNlHQ-EzfXAhvwTtmom391Ww=/350x262/post/FTjiRH8WtUO1NIV32h3e0IQHowUB.jpg",
            "W": 350,
            "H": 262
          },
          {
            "Url": "https://images.d3-x.net/uVmEKvfKDFoMubkwCwayucej71o=/700x525/post/FTjiRH8WtUO1NIV32h3e0IQHowUB.jpg",
            "W": 700,
            "H": 525
          },
          {
            "Url": "https://images.d3-x.net/dm4NxSZ7DTCFo4J9ubcUXnQp42c=/900x675/post/FTjiRH8WtUO1NIV32h3e0IQHowUB.jpg",
            "W": 900,
            "H": 675
          }
        ],
        [
          {
            "Url": "https://images.d3-x.net/ERyatA7LoEUSe7tyks4mBScK5mA=/350x262/post/FTjiRLBGtUS1NIV32h3e0IQHowUB.jpg",
            "W": 350,
            "H": 262
          },
          {
            "Url": "https://images.d3-x.net/GtKURVviFIeprruCTNJpPcHvF8w=/700x525/post/FTjiRLBGtUS1NIV32h3e0IQHowUB.jpg",
            "W": 700,
            "H": 525
          },
          {
            "Url": "https://images.d3-x.net/2YhvDkqbUxkFwEW70itHOzIr868=/900x675/post/FTjiRLBGtUS1NIV32h3e0IQHowUB.jpg",
            "W": 900,
            "H": 675
          }
        ]
      ],
      "Language": "en",
      "Source": "",
      "Featured": true,
      "LikeCount": 10
    }
  ],
  "HasMore": false,
  "Profiles": [
    {
      "Id": "FM7SRrmlBA-gW5bNWjzyxg",
      "Nickname": "bolotov",
      "Name": "Anton Bolotov",
      "Languages": [],
      "Avatar": [
        {
          "Url": "https://images.d3-x.net/wTZQUmB5juVY1iUUSkmfUhW_qG0=/60x60/avatar/FM7SRo-FBA6gW5bNWjzyxsgByAEB.jpg",
          "W": 60,
          "H": 60
        },
        {
          "Url": "https://images.d3-x.net/NYWUQHfbBot2J9Va4UWv0tis9p4=/200x200/avatar/FM7SRo-FBA6gW5bNWjzyxsgByAEB.jpg",
          "W": 200,
          "H": 200
        }
      ],
      "Cars": [
        {
          "GenerationId": "AAAAAAAAErYAAAAAAAAAAA",
          "BrandId": "AAAAAAAAABQAAAAAAAAAAA"
        }
      ]
    },
    {
      "Id": "FNfEkUUjZ6NS_bLulMhIYw",
      "Nickname": "Bazilier",
      "Name": "Kirill Bazilier",
      "Languages": [
        "ru"
      ],
      "Avatar": [
        {
          "Url": "https://images.d3-x.net/RRhbbFAWlKTSaGcWo-y8LX0GVD4=/60x60/avatar/FNfFFuL47fZwoGwLhrrtq9gE2AQB.jpg",
          "W": 60,
          "H": 60
        },
        {
          "Url": "https://images.d3-x.net/1vL9AB_HPnJp5bqySMKjl1z_WvE=/200x200/avatar/FNfFFuL47fZwoGwLhrrtq9gE2AQB.jpg",
          "W": 200,
          "H": 200
        }
      ]
    },
    {
      "Id": "FNjV_ZbOYaOylLw1MLvABw",
      "Nickname": "Tzizzo",
      "Name": "Tom Zizzo",
      "Languages": [
        "en"
      ],
      "Avatar": [
        {
          "Url": "https://images.d3-x.net/pCqow9tWQ8CgDFFj5JwTzD7rOBw=/60x60/avatar/FNjWBN-eYaWylLw1MLvAB5wEnAQB.jpg",
          "W": 60,
          "H": 60
        },
        {
          "Url": "https://images.d3-x.net/PpzdvgnMK-bNKkmdPecxyFsCF9o=/200x200/avatar/FNjWBN-eYaWylLw1MLvAB5wEnAQB.jpg",
          "W": 200,
          "H": 200
        }
      ]
    },
    {
      "Id": "FOBWsl_csrZk3x0LX2xAeQ",
      "Nickname": "AMichalik",
      "Languages": []
    },
    {
      "Id": "FOBhuM6mN3Qw8CgQtzKKSA",
      "Nickname": "Branislav",
      "Languages": []
    },
    {
      "Id": "FPHOCZO82eGKEPZ2YQphUQ",
      "Nickname": "HAGG",
      "Name": "Ross Muir",
      "Languages": [
        "en"
      ],
      "Avatar": [
        {
          "Url": "https://images.d3-x.net/kTC2e95kQdTV9fpF07pX4kkmDiA=/60x60/avatar/FPHOT0LM2eOKEPZ2YQphUeAD4AMB.jpg",
          "W": 60,
          "H": 60
        },
        {
          "Url": "https://images.d3-x.net/7I-A27YbeZi1DABx_3kkj8ZKf6s=/200x200/avatar/FPHOT0LM2eOKEPZ2YQphUeAD4AMB.jpg",
          "W": 200,
          "H": 200
        }
      ]
    }
  ],
  "Channels": [
    {
      "Id": "FNVt5Ptn8rDBdZFN6GDObg",
      "Caption": "Motorsport"
    },
    {
      "Id": "FNVt5rPHQEw0TO9bcp2GCw",
      "Caption": "Auto Business"
    },
    {
      "Id": "FNVt6Dkn8rHBdZFN6GDObg",
      "Caption": "Car Tuning"
    },
    {
      "Id": "FNVt6lEHQE00TO9bcp2GCw",
      "Caption": "Celebrities"
    },
    {
      "Id": "FNVt9b5X8rPBdZFN6GDObg",
      "Caption": "Electric Vehicles"
    },
    {
      "Id": "FNVt-FknQE80TO9bcp2GCw",
      "Caption": "Concept Cars"
    },
    {
      "Id": "FNVt-4HXQFA0TO9bcp2GCw",
      "Caption": "Hybrid Cars"
    },
    {
      "Id": "FNVt_vI3QFE0TO9bcp2GCw",
      "Caption": "Luxury Vehicles"
    },
    {
      "Id": "FNVuA2GX8rjBdZFN6GDObg",
      "Caption": "Old School"
    },
    {
      "Id": "FNVuCH5XQFQ0TO9bcp2GCw",
      "Caption": "Self-Driving Cars"
    },
    {
      "Id": "FNVuCuZXQFU0TO9bcp2GCw",
      "Caption": "Sports Cars"
    },
    {
      "Id": "FNVuDMJXQFY0TO9bcp2GCw",
      "Caption": "Styling"
    },
    {
      "Id": "FNVuDg138rvBdZFN6GDObg",
      "Caption": "SUVs and Crossovers"
    },
    {
      "Id": "FNVuDyinQFc0TO9bcp2GCw",
      "Caption": "Technology"
    },
    {
      "Id": "FNVuEHBH8rzBdZFN6GDObg",
      "Caption": "Trucks"
    },
    {
      "Id": "FOIFE4_nEofCtdpCSNcRQg",
      "Caption": "Spy Shots"
    },
    {
      "Id": "FOZ4IwhSmzhxaG9g-XSE3w",
      "Caption": "Car of the Day"
    },
    {
      "Id": "FOtkyyx4Ez-siqzw4-7MgQ",
      "Caption": "Video of the Day"
    },
    {
      "Id": "FPZjes9eoFlsJQsj_nqoYA",
      "Caption": "Quiz of the Day"
    }
  ]
}